setup.cfg
setup.py
seaborn_games/__init__.py
seaborn_games/git_commands.py
seaborn_games/test_all.py
seaborn_games.egg-info/PKG-INFO
seaborn_games.egg-info/SOURCES.txt
seaborn_games.egg-info/dependency_links.txt
seaborn_games.egg-info/entry_points.txt
seaborn_games.egg-info/requires.txt
seaborn_games.egg-info/top_level.txt