Metadata-Version: 1.1
Name: seaborn-games
Version: 0.0.3
Summary: SeabornGames installs all of the SeabornGames repositories
Home-page: https://github.com/SeabornGames/File
Author: Ben Christenson
Author-email: Python@BenChristenson.com
License: MIT License
Download-URL: https://github.com/SeabornGames/Games/tarball/download
Platform: UNKNOWN
Classifier: Intended Audience :: Developers
Classifier: Natural Language :: English
Classifier: License :: Other/Proprietary License
Classifier: Operating System :: POSIX :: Linux
Classifier: Programming Language :: Python
Classifier: Programming Language :: Python :: 2.7
Classifier: Programming Language :: Python :: 3.6
